<?xml version="1.0" standalone="yes"?>
<Titles>
  <TYPE_OF_PAGE>Types of page</TYPE_OF_PAGE>
  <MENU_TYPE>Types of menu</MENU_TYPE>
  <SECTIONS>Sections</SECTIONS>
  <CATEGORIES>Categories</CATEGORIES>

  <!--****************************Begin: TUYENDV*********************************-->
  <MSG_UPDATE_SUCCESFULLY>Update successfully</MSG_UPDATE_SUCCESFULLY>
  <MSG_HAVE_NO_PERMISSION>You don't have permission for this item</MSG_HAVE_NO_PERMISSION>

  <PAGE_PERMISSION_MENU>Permission Manager</PAGE_PERMISSION_MENU>
  <PAGE_RULE_ASSIGNMENT>Rule Assignment</PAGE_RULE_ASSIGNMENT>
  
  <LIST_OF_MENU>List of Menus</LIST_OF_MENU>
  <RULE_MANAGEMENT>Rule Management</RULE_MANAGEMENT>
  <RULE_NAME>Rule's name</RULE_NAME>
  <DESCRIPTION>Description</DESCRIPTION>

  <MENU_MANAGEMENT>Menu Management</MENU_MANAGEMENT>
  <MENU_DETAILS>The details of Menu</MENU_DETAILS>
  <MENU_LIST>List of menus</MENU_LIST>
  <MENU_TYPE_LIST>List of Menu Types</MENU_TYPE_LIST>
  <MENU_URL>URL</MENU_URL>
  <MENU_STT>Order</MENU_STT>
  <TITLE>Title</TITLE>
  <CODE>Code</CODE>
  <USER_STATUS>User Status</USER_STATUS>
  <USER_LIST>List of Users</USER_LIST>

  <MENU_PARENT>Parent Menu</MENU_PARENT>

  <RULE>Choose Rules</RULE>
  <ACTION>Action</ACTION>
  <SECTION_TITLE>Name</SECTION_TITLE>
  <PUBLISHED>Status</PUBLISHED>
  <ORDERING>Order</ORDERING>  
    
  <TITLE_ICON>.</TITLE_ICON>

  <BUTTON_CANCEL>Hủy</BUTTON_CANCEL>
  <BUTTON_BACK>Quay lại</BUTTON_BACK>
  <BUTTON_SUBMIT>Lưu</BUTTON_SUBMIT>
  <BUTTON_CREATE>Tạo mới</BUTTON_CREATE>
  <BUTTON_EXPORT>Xuất file</BUTTON_EXPORT>
  <BUTTON_PREVIEW>Xem trước</BUTTON_PREVIEW>
  <BUTTON_APPROVE>Chốt</BUTTON_APPROVE>
  <BUTTON_SEARCH>Tìm kiếm</BUTTON_SEARCH>
  <!--****************************End: TUYENDV*********************************-->

  <!--****************************Begin: URL*********************************-->  
  <URL_ADD_NHAN_VIEN>/Modules/QuanLyNhanSu/FrmNhanVienCT.aspx</URL_ADD_NHAN_VIEN>
  <URL_MENUS>/Modules/MenuChucNang.aspx</URL_MENUS>
  <URL_ADD_MENU>/Modules/MenuChucNang_CT.aspx</URL_ADD_MENU>
  <URL_BIEU_MAU_CT>/Modules/QuanLyCongViec/BieuMau_CT.aspx</URL_BIEU_MAU_CT>  
  <URL_BIEU_MAU>/Modules/QuanLyCongViec/BieuMau.aspx</URL_BIEU_MAU>
  <URL_QUYET_DINH_CT>/Modules/QuanLyCongViec/QuyetDinh_CT.aspx</URL_QUYET_DINH_CT>
  <URL_QUYET_DINH>/Modules/QuanLyCongViec/QuyetDinh.aspx</URL_QUYET_DINH>
  <URL_LOAI_QUYET_DINH>/Modules/QuanLyCongViec/LoaiQuyetDinh.aspx</URL_LOAI_QUYET_DINH>
  <!--****************************End: URL*********************************-->

  <!--****************************Begin: VALUE CONST*********************************-->
  <BLANK_ITEM_VALUE>BLANK_ITEM</BLANK_ITEM_VALUE>
  <BLANK_ITEM_TITLE>............Click to choose...........</BLANK_ITEM_TITLE>
  
  <STATUS_ACTIVE_TITLE>Active</STATUS_ACTIVE_TITLE>
  <STATUS_ACTIVE_VALUE>1</STATUS_ACTIVE_VALUE>

  <STATUS_INACTIVE_TITLE>Inactive</STATUS_INACTIVE_TITLE>
  <STATUS_INACTIVE_VALUE>0</STATUS_INACTIVE_VALUE>
  
  <!--****************************End: VALUE CONST*********************************-->

  <!--****************************Begin: LOG MESSAGE*********************************-->
  <LOG_FILE_NAME>QLNS Log File</LOG_FILE_NAME>
  
  <LOG_MENU_CREATE>Tạo thành công menu: '{0}' </LOG_MENU_CREATE>  
  <LOG_CONTENT_FORMAT_FILE>[{0}][{1}] - {2} (URL={3})</LOG_CONTENT_FORMAT_FILE>
  <LOG_IMPORT_DB_FROM_EXCEL>[{0}][{1}]: {2} - {3}</LOG_IMPORT_DB_FROM_EXCEL>
  
  <LOG_BIEU_MAU_CAP_NHAT>Cập nhật thành công Bieu mẫu: '{0}' </LOG_BIEU_MAU_CAP_NHAT>
  <LOG_QUYET_DINH_CAP_NHAT>Cập nhật thành công Quyết định số: '{0}' </LOG_QUYET_DINH_CAP_NHAT>
  
  <!--BEGIN: Code for Import DB from Excel-->  
  <SYSTEM_AUTO>SYSTEM_AUTO</SYSTEM_AUTO>
  <SYSTEM_DATE_AUTO>01/01/2000</SYSTEM_DATE_AUTO>
  <SYSTEM_TRANG_THAI_LV_LV>LV</SYSTEM_TRANG_THAI_LV_LV>
  <!--END: Code for Import DB from Excel-->

  <!--****************************END: LOG MESSAGE*********************************-->
  
</Titles>